nmosnode/__init__.py
nmosnode/aggregator.py
nmosnode/api.py
nmosnode/authclient.py
nmosnode/facade.py
nmosnode/mock_service.py
nmosnode/nodefacadeservice.py
nmosnode/registry.py
nmosnode/serviceinterface.py
tests/__init__.py
tests/test_aggregator.py
tests/test_facade.py
tests/test_mdnsUpdater.py
tests/test_registry.py
usr/bin/nmosnode
nodefacade-0.12.4.dist-info/LICENSE.md
nodefacade-0.12.4.dist-info/METADATA
nodefacade-0.12.4.dist-info/NOTICE.md
nodefacade-0.12.4.dist-info/WHEEL
nodefacade-0.12.4.dist-info/top_level.txt
nodefacade-0.12.4.dist-info/RECORD
