Metadata-Version: 2.1
Name: nodefacade
Version: 0.12.4
Summary: BBC implementation of an AMWA NMOS Node API
Home-page: https://github.com/bbc/nmos-node
Author: Peter Brightwell
Author-email: peter.brightwell@bbc.co.uk
License: Apache 2
Platform: UNKNOWN
Requires-Dist: six
Requires-Dist: cysystemd
Requires-Dist: nmoscommon (>=0.20.0)
Requires-Dist: requests
Requires-Dist: gevent
Requires-Dist: mdnsbridge (>=0.9.2)
Requires-Dist: authlib
Requires-Dist: cryptography (>3.0.0)
